[{"Country":"Netherlands","SugarConsumption":401.0999999999999,"SaltConsumption":29.4622},
  {"Country":"Canada","SugarConsumption":714.82,"SaltConsumption":28.721923999999998},
  {"Country":"Australia","SugarConsumption":5571.880300000007,"SaltConsumption":436.8099569999999},
  {"Country":"France","SugarConsumption":289992.61430000135,"SaltConsumption":25351.076585370323},
  {"Country":"Germany","SugarConsumption":973.7800000000002,"SaltConsumption":77.93815920000003},
  {"Country":"Spain","SugarConsumption":238.04,"SaltConsumption":35.509646999999994},
  {"Country":"South Africa","SugarConsumption":100.61999999999999,"SaltConsumption":4.801759999999999},
  {"Country":"United States","SugarConsumption":17242.53600000002,"SaltConsumption":1318.9659339999992},
  {"Country":"United Kingdom","SugarConsumption":17502.76399999997,"SaltConsumption":808.9604749999955}]
